key_typeddict/__init__.py
key_typeddict/core.py
key_typeddict/core.pyi
key_typeddict/plugin.py
key_typeddict/py.typed
key_typeddict-0.1.0.dist-info/LICENSE.txt
key_typeddict-0.1.0.dist-info/METADATA
key_typeddict-0.1.0.dist-info/WHEEL
key_typeddict-0.1.0.dist-info/top_level.txt
key_typeddict-0.1.0.dist-info/RECORD
