Metadata-Version: 2.1
Name: key-typeddict
Version: 0.1.0
Summary: mypy_extensions.TypedDict with some additional features
Home-page: https://github.com/mkurnikov/key-typeddict
Author: Maksim Kurnikov
Author-email: maxim.kurnikov@gmail.com
License: MIT
Platform: UNKNOWN
Requires-Dist: mypy (>=0.670)
Requires-Dist: dataclasses
